setup.py
Aspose_Words_java_for_jython_v1.0.egg-info/PKG-INFO
Aspose_Words_java_for_jython_v1.0.egg-info/SOURCES.txt
Aspose_Words_java_for_jython_v1.0.egg-info/dependency_links.txt
Aspose_Words_java_for_jython_v1.0.egg-info/top_level.txt
asposewords/__init__.py