Metadata-Version: 1.1
Name: Aspose-Words-java-for-jython-v1.0
Version: 1.0
Summary: Aspose.Words for Jython allows you to use Aspose.Words for Java API in your Jython applications
Home-page: UNKNOWN
Author: Fahad Adeel
Author-email: words@aspose.com
License: UNKNOWN
Platform: UNKNOWN
Classifier: Programming Language :: Python
Classifier: Programming Language :: Python :: 2
Classifier: License :: OSI Approved :: MIT License
Classifier: Operating System :: OS Independent
